{
  "resource": "PasswordReset",
  "http_method": "POST",
  "route": "/v1/password-resets/",
  "description": "POST create",
  "explanation": null,
  "parameters": [
    {
      "required": true,
      "name": "type",
      "description": " type"
    },
    {
      "scope": "attributes",
      "required": true,
      "name": "old-password",
      "description": "Attributes old-password"
    },
    {
      "scope": "attributes",
      "required": true,
      "name": "new-password",
      "description": "Attributes new-password"
    },
    {
      "scope": "attributes",
      "required": true,
      "name": "user-id",
      "description": "Attributes user-id"
    }
  ],
  "response_fields": [

  ],
  "requests": [
    {
      "request_method": "POST",
      "request_path": "/v1/password-resets/",
      "request_body": "{\"data\":{\"type\":\"password-resets\",\"attributes\":{\"old-password\":\"Password123\",\"new-password\":\"NEW_pass\",\"user-id\":1}}}",
      "request_headers": {
        "Authorization": "Bearer c452297afa963520580028cb7ce8a252eaecbd63d1e419d51954f994e2b0c406",
        "Content-Type": "application/vnd.api+json"
      },
      "request_query_parameters": {
      },
      "request_content_type": "application/vnd.api+json",
      "response_status": 201,
      "response_status_text": "Created",
      "response_body": "{\"data\":{\"id\":\"2017-01-07 21:43:46 UTC\",\"type\":\"password-resets\",\"links\":{\"self\":\"http://example.org/v1/password-resets/2017-01-07 21:43:46 UTC\"},\"attributes\":{\"created-at\":\"2017-01-07T21:43:46.603Z\",\"updated-at\":\"2017-01-07T21:43:46.603Z\",\"new-password\":\"NEW_pass\",\"old-password\":\"Password123\",\"user-id\":1}}}",
      "response_headers": {
        "Content-Type": "application/vnd.api+json; charset=utf-8"
      },
      "response_content_type": "application/vnd.api+json; charset=utf-8",
      "curl": null
    }
  ]
}