{
  "resource": "Organization",
  "http_method": "GET",
  "route": "/v1/organizations/",
  "description": "GET index",
  "explanation": null,
  "parameters": [

  ],
  "response_fields": [

  ],
  "requests": [
    {
      "request_method": "GET",
      "request_path": "/v1/organizations/",
      "request_body": null,
      "request_headers": {
        "Authorization": "Bearer 66ba7104fa91b26f490b1922a1da697eda4d4fb10c8c1984bb96ccea776a2897"
      },
      "request_query_parameters": {
      },
      "request_content_type": null,
      "response_status": 200,
      "response_status_text": "OK",
      "response_body": "{\"data\":[{\"id\":\"35\",\"type\":\"organizations\",\"links\":{\"self\":\"http://example.org/v1/organizations/35\"},\"attributes\":{\"created-at\":\"2017-01-07T21:43:47.430Z\",\"updated-at\":\"2017-01-07T21:43:47.430Z\",\"name\":\"This is the name\",\"address\":null,\"phone\":null,\"url\":null,\"email\":null},\"relationships\":{\"memberships\":{\"links\":{\"self\":\"http://example.org/v1/organizations/35/relationships/memberships\",\"related\":\"http://example.org/v1/organizations/35/memberships\"}},\"users\":{\"links\":{\"self\":\"http://example.org/v1/organizations/35/relationships/users\",\"related\":\"http://example.org/v1/organizations/35/users\"}}}},{\"id\":\"36\",\"type\":\"organizations\",\"links\":{\"self\":\"http://example.org/v1/organizations/36\"},\"attributes\":{\"created-at\":\"2017-01-07T21:43:47.432Z\",\"updated-at\":\"2017-01-07T21:43:47.432Z\",\"name\":\"Acme Inc.\",\"address\":null,\"phone\":null,\"url\":null,\"email\":null},\"relationships\":{\"memberships\":{\"links\":{\"self\":\"http://example.org/v1/organizations/36/relationships/memberships\",\"related\":\"http://example.org/v1/organizations/36/memberships\"}},\"users\":{\"links\":{\"self\":\"http://example.org/v1/organizations/36/relationships/users\",\"related\":\"http://example.org/v1/organizations/36/users\"}}}},{\"id\":\"37\",\"type\":\"organizations\",\"links\":{\"self\":\"http://example.org/v1/organizations/37\"},\"attributes\":{\"created-at\":\"2017-01-07T21:43:47.440Z\",\"updated-at\":\"2017-01-07T21:43:47.440Z\",\"name\":\"Acme Inc.\",\"address\":null,\"phone\":null,\"url\":null,\"email\":null},\"relationships\":{\"memberships\":{\"links\":{\"self\":\"http://example.org/v1/organizations/37/relationships/memberships\",\"related\":\"http://example.org/v1/organizations/37/memberships\"}},\"users\":{\"links\":{\"self\":\"http://example.org/v1/organizations/37/relationships/users\",\"related\":\"http://example.org/v1/organizations/37/users\"}}}}],\"meta\":{\"record-count\":3},\"links\":{\"first\":\"http://example.org/v1/organizations?page%5Blimit%5D=10\\u0026page%5Boffset%5D=0\",\"last\":\"http://example.org/v1/organizations?page%5Blimit%5D=10\\u0026page%5Boffset%5D=0\"}}",
      "response_headers": {
        "Content-Type": "application/vnd.api+json; charset=utf-8"
      },
      "response_content_type": "application/vnd.api+json; charset=utf-8",
      "curl": null
    }
  ]
}